opperai/__init__.py
opperai/_hooks/__init__.py
opperai/_hooks/registration.py
opperai/_hooks/sdkhooks.py
opperai/_hooks/types.py
opperai/_version.py
opperai/analytics.py
opperai/basesdk.py
opperai/datasets.py
opperai/embeddings.py
opperai/entries.py
opperai/errors/__init__.py
opperai/errors/apierror.py
opperai/errors/badrequesterror.py
opperai/errors/conflicterror.py
opperai/errors/error.py
opperai/errors/no_response_error.py
opperai/errors/notfounderror.py
opperai/errors/oppererror.py
opperai/errors/requestvalidationerror.py
opperai/errors/responsevalidationerror.py
opperai/errors/unauthorizederror.py
opperai/functions.py
opperai/httpclient.py
opperai/knowledge.py
opperai/language_models.py
opperai/models/__init__.py
opperai/models/add_knowledge_knowledge_base_id_add_postop.py
opperai/models/addrequest.py
opperai/models/annotation.py
opperai/models/annotationurlcitation.py
opperai/models/app_api_public_v2_function_call_callfunctionrequest.py
opperai/models/app_api_public_v2_function_call_callfunctionresponse.py
opperai/models/app_api_public_v2_functions_callfunctionrequest.py
opperai/models/app_api_public_v2_functions_callfunctionresponse.py
opperai/models/audio.py
opperai/models/body_upload_file_knowledge_knowledge_base_id_upload_post.py
opperai/models/call_function_functions_function_id_call_postop.py
opperai/models/call_function_revision_functions_function_id_call_revision_id_postop.py
opperai/models/chat_completions_openai_chat_completions_postop.py
opperai/models/chatcompletion.py
opperai/models/chatcompletionallowedtoolchoiceparam.py
opperai/models/chatcompletionallowedtoolsparam.py
opperai/models/chatcompletionassistantmessageparam.py
opperai/models/chatcompletionaudio.py
opperai/models/chatcompletionaudioparam.py
opperai/models/chatcompletioncontentpartimageparam.py
opperai/models/chatcompletioncontentpartinputaudioparam.py
opperai/models/chatcompletioncontentpartrefusalparam.py
opperai/models/chatcompletioncontentparttextparam.py
opperai-1.7.1.dist-info/METADATA
opperai-1.7.1.dist-info/WHEEL
opperai-1.7.1.dist-info/RECORD
